{
    "Business": {
        "ABN": "220 96 96",
        "Name": "Wake Up with Coffee"
    },
    "Cashier": "Diane",
    "Date": "2027/11/02",
    "GST": 6.15,
    "Payments": [
        {
            "Amount": 33.8,
            "Method": "BPAY"
        },
        {
            "Amount": 33.8,
            "Method": "Credit Card"
        }
    ],
    "Products": [
        {
            "Cost": 4.1,
            "Name": "Cappuccino",
            "Price": 6.4,
            "Quantity": 1
        },
        {
            "Cost": 6.7,
            "Name": "Ham bagel",
            "Price": 12.8,
            "Quantity": 2
        },
        {
            "Cost": 3.1,
            "Name": "Cupcake",
            "Price": 8.9,
            "Quantity": 2
        },
        {
            "Cost": 3.1,
            "Name": "Cupcake",
            "Price": 8.9,
            "Quantity": 2
        }
    ],
    "Promotions": [],
    "Reference": "2209696:271102:02907",
    "Sequence": 2907,
    "Terminal": 4,
    "Total": 67.6
}