{
    "Business": {
        "ABN": "220 96 96",
        "Name": "Wake Up with Coffee"
    },
    "Cashier": "Diane",
    "Customer": {
        "Name": "Daniel",
        "Points_Earnt": 1780
    },
    "Date": "2027/12/02",
    "GST": 1.62,
    "Payments": [
        {
            "Amount": 17.8,
            "Method": "BPAY"
        }
    ],
    "Products": [
        {
            "Cost": 3.1,
            "Name": "Cupcake",
            "Price": 8.9,
            "Quantity": 2
        }
    ],
    "Promotions": [],
    "Reference": "2209696:271202:02963",
    "Sequence": 2963,
    "Terminal": 4,
    "Total": 17.8
}