{
    "Business": {
        "ABN": "220 96 96",
        "Name": "Wake Up with Coffee"
    },
    "Cashier": "Leslie",
    "Date": "2024/11/23",
    "GST": 5.2,
    "Payments": [
        {
            "Amount": 50.2,
            "Method": "Cash"
        },
        {
            "Amount": 7.0,
            "Method": "BPAY"
        }
    ],
    "Products": [
        {
            "Cost": 2.8,
            "Name": "English muffin",
            "Price": 6.6,
            "Quantity": 3
        },
        {
            "Cost": 2.8,
            "Name": "English muffin",
            "Price": 6.6,
            "Quantity": 3
        },
        {
            "Cost": 1.4,
            "Name": "Glazed donut",
            "Price": 4.4,
            "Quantity": 1
        },
        {
            "Cost": 4.2,
            "Name": "Salmon bagel",
            "Price": 13.2,
            "Quantity": 2
        }
    ],
    "Promotions": [
        {
            "Discount": 0.05,
            "Per_Quantity": 1,
            "Product": "Salmon bagel"
        },
        {
            "Discount": 0.3,
            "Per_Quantity": 2,
            "Product": "English muffin"
        }
    ],
    "Reference": "2209696:241123:01176",
    "Sequence": 1176,
    "Terminal": 3,
    "Total": 57.2
}