{
    "Business": {
        "ABN": "379 58 98",
        "Name": "Ed's Barber Supplies"
    },
    "Cashier": "Justin",
    "Date": "2029/04/12",
    "GST": 29.72,
    "Payments": [
        {
            "Amount": 228.87,
            "Method": "EFTPOS"
        },
        {
            "Amount": 98.09,
            "Method": "Credit Card"
        }
    ],
    "Products": [
        {
            "Cost": 7.6,
            "Name": "Pomade",
            "Price": 17.6,
            "Quantity": 2
        },
        {
            "Cost": 7.6,
            "Name": "Pomade",
            "Price": 17.6,
            "Quantity": 3
        },
        {
            "Cost": 20.6,
            "Name": "Cape white",
            "Price": 61.5,
            "Quantity": 3
        },
        {
            "Cost": 20.6,
            "Name": "Cape white",
            "Price": 61.5,
            "Quantity": 1
        }
    ],
    "Promotions": [
        {
            "Discount": 0.1,
            "Per_Quantity": 2,
            "Product": "Pomade"
        }
    ],
    "Reference": "3795898:290412:02766",
    "Sequence": 2766,
    "Terminal": 2,
    "Total": 326.96
}