{
    "Business": {
        "ABN": "379 58 98",
        "Name": "Ed's Barber Supplies"
    },
    "Cashier": "Barbara",
    "Customer": {
        "Name": "Linda",
        "Points_Earnt": 13070
    },
    "Date": "2029/03/12",
    "GST": 11.88,
    "Payments": [
        {
            "Amount": 52.28,
            "Method": "Credit Card"
        },
        {
            "Amount": 78.42,
            "Method": "BPAY"
        }
    ],
    "Products": [
        {
            "Cost": 7.7,
            "Name": "Hairwax",
            "Price": 17.6,
            "Quantity": 3
        },
        {
            "Cost": 7.6,
            "Name": "Pomade",
            "Price": 17.6,
            "Quantity": 1
        },
        {
            "Cost": 7.7,
            "Name": "Hairwax",
            "Price": 17.6,
            "Quantity": 1
        },
        {
            "Cost": 11.6,
            "Name": "Spray bottle",
            "Price": 26.8,
            "Quantity": 3
        }
    ],
    "Promotions": [
        {
            "Discount": 0.25,
            "Per_Quantity": 1,
            "Product": "Spray bottle"
        },
        {
            "Discount": 0.25,
            "Per_Quantity": 1,
            "Product": "Hairwax"
        }
    ],
    "Reference": "3795898:290312:02728",
    "Sequence": 2728,
    "Terminal": 2,
    "Total": 130.7
}