{
    "Business": {
        "ABN": "379 58 98",
        "Name": "Ed's Barber Supplies"
    },
    "Cashier": "Jonathon",
    "Customer": {
        "Name": "Scott",
        "Points_Earnt": 0
    },
    "Date": "2025/05/15",
    "GST": 20.36,
    "Payments": [
        {
            "Amount": 224.0,
            "Method": "Loyalty Points"
        }
    ],
    "Products": [
        {
            "Cost": 14.2,
            "Name": "Broom",
            "Price": 44.8,
            "Quantity": 3
        },
        {
            "Cost": 14.2,
            "Name": "Broom",
            "Price": 44.8,
            "Quantity": 2
        }
    ],
    "Promotions": [],
    "Reference": "3795898:250515:01071",
    "Sequence": 1071,
    "Terminal": 5,
    "Total": 224.0
}