{
    "Business": {
        "ABN": "379 58 98",
        "Name": "Ed's Barber Supplies"
    },
    "Cashier": "Eric",
    "Customer": {
        "Name": "Kelly",
        "Points_Earnt": 0
    },
    "Date": "2024/05/13",
    "GST": 3.99,
    "Payments": [
        {
            "Amount": 43.92,
            "Method": "Loyalty Points"
        }
    ],
    "Products": [
        {
            "Cost": 20.4,
            "Name": "Cape grey",
            "Price": 48.8,
            "Quantity": 1
        }
    ],
    "Promotions": [
        {
            "Discount": 0.1,
            "Per_Quantity": 1,
            "Product": "Cape grey"
        }
    ],
    "Reference": "3795898:240513:00677",
    "Sequence": 677,
    "Terminal": 1,
    "Total": 43.92
}