{
    "Business": {
        "ABN": "379 58 98",
        "Name": "Ed's Barber Supplies"
    },
    "Cashier": "Natasha",
    "Customer": {
        "Name": "Ashlee",
        "Points_Earnt": 5920
    },
    "Date": "2028/11/10",
    "GST": 5.38,
    "Payments": [
        {
            "Amount": 59.2,
            "Method": "BPAY"
        }
    ],
    "Products": [
        {
            "Cost": 7.1,
            "Name": "Pomade",
            "Price": 16.6,
            "Quantity": 1
        },
        {
            "Cost": 10.8,
            "Name": "Spray bottle",
            "Price": 25.4,
            "Quantity": 1
        },
        {
            "Cost": 5.7,
            "Name": "Soap 500mL",
            "Price": 8.6,
            "Quantity": 2
        }
    ],
    "Promotions": [],
    "Reference": "3795898:281110:02568",
    "Sequence": 2568,
    "Terminal": 3,
    "Total": 59.2
}