{
    "Business": {
        "ABN": "379 58 98",
        "Name": "Ed's Barber Supplies"
    },
    "Cashier": "Jonathon",
    "Customer": {
        "Name": "Darren",
        "Points_Earnt": 31977
    },
    "Date": "2025/05/30",
    "GST": 29.07,
    "Payments": [
        {
            "Amount": 127.91,
            "Method": "EFTPOS"
        },
        {
            "Amount": 191.86,
            "Method": "Debit Card"
        }
    ],
    "Products": [
        {
            "Cost": 20.8,
            "Name": "Scissors",
            "Price": 39.8,
            "Quantity": 3
        },
        {
            "Cost": 20.8,
            "Name": "Scissors",
            "Price": 39.8,
            "Quantity": 3
        },
        {
            "Cost": 29.0,
            "Name": "Clippers kit",
            "Price": 56.5,
            "Quantity": 2
        },
        {
            "Cost": 10.6,
            "Name": "Razorblade",
            "Price": 17.2,
            "Quantity": 2
        }
    ],
    "Promotions": [
        {
            "Discount": 0.2,
            "Per_Quantity": 2,
            "Product": "Scissors"
        },
        {
            "Discount": 0.15,
            "Per_Quantity": 2,
            "Product": "Clippers kit"
        },
        {
            "Discount": 0.05,
            "Per_Quantity": 2,
            "Product": "Razorblade"
        }
    ],
    "Reference": "3795898:250530:01087",
    "Sequence": 1087,
    "Terminal": 5,
    "Total": 319.77
}