{
    "Business": {
        "ABN": "379 58 98",
        "Name": "Ed's Barber Supplies"
    },
    "Cashier": "Eric",
    "Customer": {
        "Name": "Catherine",
        "Points_Earnt": 26860
    },
    "Date": "2026/05/26",
    "GST": 24.42,
    "Payments": [
        {
            "Amount": 268.6,
            "Method": "EFTPOS"
        }
    ],
    "Products": [
        {
            "Cost": 15.2,
            "Name": "Broom",
            "Price": 47.2,
            "Quantity": 1
        },
        {
            "Cost": 22.0,
            "Name": "Scissors",
            "Price": 42.0,
            "Quantity": 1
        },
        {
            "Cost": 15.2,
            "Name": "Broom",
            "Price": 47.2,
            "Quantity": 3
        },
        {
            "Cost": 22.0,
            "Name": "Scissors",
            "Price": 42.0,
            "Quantity": 1
        }
    ],
    "Promotions": [
        {
            "Discount": 0.05,
            "Per_Quantity": 1,
            "Product": "Scissors"
        }
    ],
    "Reference": "3795898:260526:01487",
    "Sequence": 1487,
    "Terminal": 1,
    "Total": 268.6
}