{
    "Business": {
        "ABN": "379 58 98",
        "Name": "Ed's Barber Supplies"
    },
    "Cashier": "Jonathon",
    "Date": "2025/10/30",
    "GST": 8.05,
    "Payments": [
        {
            "Amount": 44.3,
            "Method": "EFTPOS"
        },
        {
            "Amount": 44.3,
            "Method": "Debit Card"
        }
    ],
    "Products": [
        {
            "Cost": 21.4,
            "Name": "Cape grey",
            "Price": 51.0,
            "Quantity": 1
        },
        {
            "Cost": 21.4,
            "Name": "Cape grey",
            "Price": 51.0,
            "Quantity": 1
        },
        {
            "Cost": 10.6,
            "Name": "Razorblade",
            "Price": 17.2,
            "Quantity": 1
        }
    ],
    "Promotions": [
        {
            "Discount": 0.3,
            "Per_Quantity": 2,
            "Product": "Cape grey"
        }
    ],
    "Reference": "3795898:251030:01254",
    "Sequence": 1254,
    "Terminal": 2,
    "Total": 88.6
}