{
    "Business": {
        "ABN": "379 58 98",
        "Name": "Ed's Barber Supplies"
    },
    "Cashier": "Kathryn",
    "Customer": {
        "Name": "Ashlee",
        "Points_Earnt": 31025
    },
    "Date": "2025/01/06",
    "GST": 28.2,
    "Payments": [
        {
            "Amount": 89.25,
            "Method": "Cash"
        },
        {
            "Amount": 221.0,
            "Method": "EFTPOS"
        }
    ],
    "Products": [
        {
            "Cost": 21.4,
            "Name": "Cape grey",
            "Price": 51.0,
            "Quantity": 3
        },
        {
            "Cost": 21.4,
            "Name": "Cape grey",
            "Price": 51.0,
            "Quantity": 3
        },
        {
            "Cost": 29.0,
            "Name": "Clippers kit",
            "Price": 56.5,
            "Quantity": 2
        }
    ],
    "Promotions": [
        {
            "Discount": 0.15,
            "Per_Quantity": 2,
            "Product": "Clippers kit"
        },
        {
            "Discount": 0.3,
            "Per_Quantity": 2,
            "Product": "Cape grey"
        }
    ],
    "Reference": "3795898:250106:00928",
    "Sequence": 928,
    "Terminal": 4,
    "Total": 310.25
}