{
    "Business": {
        "ABN": "379 58 98",
        "Name": "Ed's Barber Supplies"
    },
    "Cashier": "Carlos",
    "Customer": {
        "Name": "Anna",
        "Points_Earnt": 8400
    },
    "Date": "2029/02/21",
    "GST": 7.64,
    "Payments": [
        {
            "Amount": 84.0,
            "Method": "Gift Card"
        }
    ],
    "Products": [
        {
            "Cost": 5.5,
            "Name": "Hair tonic",
            "Price": 16.6,
            "Quantity": 2
        },
        {
            "Cost": 5.5,
            "Name": "Hair tonic",
            "Price": 16.6,
            "Quantity": 2
        },
        {
            "Cost": 7.6,
            "Name": "Pomade",
            "Price": 17.6,
            "Quantity": 1
        }
    ],
    "Promotions": [],
    "Reference": "3795898:290221:02700",
    "Sequence": 2700,
    "Terminal": 4,
    "Total": 84.0
}