{
    "Business": {
        "ABN": "559 38 22",
        "Name": "Penguin Swim School"
    },
    "Cashier": "Jennifer",
    "Customer": {
        "Name": "Charles",
        "Points_Earnt": 3360
    },
    "Date": "2024/12/11",
    "GST": 3.05,
    "Payments": [
        {
            "Amount": 23.52,
            "Method": "EFTPOS"
        },
        {
            "Amount": 10.08,
            "Method": "BPAY"
        }
    ],
    "Products": [
        {
            "Cost": 3.4,
            "Name": "Swim cap",
            "Price": 11.2,
            "Quantity": 3
        }
    ],
    "Promotions": [],
    "Reference": "5593822:241211:00743",
    "Sequence": 743,
    "Terminal": 3,
    "Total": 33.6
}