{
    "Business": {
        "ABN": "559 38 22",
        "Name": "Penguin Swim School"
    },
    "Cashier": "Kevin",
    "Customer": {
        "Name": "Kenneth",
        "Points_Earnt": 14440
    },
    "Date": "2028/06/24",
    "GST": 13.13,
    "Payments": [
        {
            "Amount": 144.4,
            "Method": "EFTPOS"
        }
    ],
    "Products": [
        {
            "Cost": 12.4,
            "Name": "Infant lesson",
            "Price": 19.6,
            "Quantity": 3
        },
        {
            "Cost": 2.2,
            "Name": "Egg+Bac burger",
            "Price": 6.7,
            "Quantity": 2
        },
        {
            "Cost": 3.1,
            "Name": "Hot chips",
            "Price": 6.7,
            "Quantity": 2
        },
        {
            "Cost": 12.4,
            "Name": "Infant lesson",
            "Price": 19.6,
            "Quantity": 3
        }
    ],
    "Promotions": [],
    "Reference": "5593822:280624:02003",
    "Sequence": 2003,
    "Terminal": 2,
    "Total": 144.4
}