{
    "Business": {
        "ABN": "559 38 22",
        "Name": "Penguin Swim School"
    },
    "Cashier": "Kevin",
    "Customer": {
        "Name": "Steven",
        "Points_Earnt": 16602
    },
    "Date": "2024/01/29",
    "GST": 15.09,
    "Payments": [
        {
            "Amount": 153.9,
            "Method": "Cash"
        },
        {
            "Amount": 12.12,
            "Method": "Debit Card"
        }
    ],
    "Products": [
        {
            "Cost": 2.5,
            "Name": "Water bottle",
            "Price": 7.8,
            "Quantity": 2
        },
        {
            "Cost": 9.5,
            "Name": "Adult class",
            "Price": 18.8,
            "Quantity": 3
        },
        {
            "Cost": 9.5,
            "Name": "Adult class",
            "Price": 18.8,
            "Quantity": 3
        },
        {
            "Cost": 11.4,
            "Name": "Sync diving",
            "Price": 22.0,
            "Quantity": 3
        }
    ],
    "Promotions": [
        {
            "Discount": 0.3,
            "Per_Quantity": 2,
            "Product": "Sync diving"
        },
        {
            "Discount": 0.1,
            "Per_Quantity": 2,
            "Product": "Adult class"
        },
        {
            "Discount": 0.25,
            "Per_Quantity": 1,
            "Product": "Water bottle"
        }
    ],
    "Reference": "5593822:240129:00469",
    "Sequence": 469,
    "Terminal": 4,
    "Total": 166.02
}