{
    "Business": {
        "ABN": "559 38 22",
        "Name": "Penguin Swim School"
    },
    "Cashier": "Kevin",
    "Customer": {
        "Name": "William",
        "Points_Earnt": 3560
    },
    "Date": "2027/01/11",
    "GST": 3.24,
    "Payments": [
        {
            "Amount": 35.6,
            "Method": "EFTPOS"
        }
    ],
    "Products": [
        {
            "Cost": 2.1,
            "Name": "Egg+Bac burger",
            "Price": 6.4,
            "Quantity": 2
        },
        {
            "Cost": 4.1,
            "Name": "Casual access",
            "Price": 7.6,
            "Quantity": 3
        }
    ],
    "Promotions": [],
    "Reference": "5593822:270111:01483",
    "Sequence": 1483,
    "Terminal": 3,
    "Total": 35.6
}