{
    "Business": {
        "ABN": "559 38 22",
        "Name": "Penguin Swim School"
    },
    "Cashier": "Jennifer",
    "Date": "2023/01/25",
    "GST": 1.3,
    "Payments": [
        {
            "Amount": 2.86,
            "Method": "EFTPOS"
        },
        {
            "Amount": 11.45,
            "Method": "Gift Card"
        }
    ],
    "Products": [
        {
            "Cost": 2.7,
            "Name": "Shampoo",
            "Price": 5.3,
            "Quantity": 3
        }
    ],
    "Promotions": [
        {
            "Discount": 0.1,
            "Per_Quantity": 1,
            "Product": "Shampoo"
        }
    ],
    "Reference": "5593822:230125:00154",
    "Sequence": 154,
    "Terminal": 4,
    "Total": 14.31
}