{
    "Business": {
        "ABN": "559 38 22",
        "Name": "Penguin Swim School"
    },
    "Cashier": "Kevin",
    "Customer": {
        "Name": "Scott",
        "Points_Earnt": 4632
    },
    "Date": "2028/02/02",
    "GST": 4.21,
    "Payments": [
        {
            "Amount": 46.32,
            "Method": "BPAY"
        }
    ],
    "Products": [
        {
            "Cost": 14.2,
            "Name": "Sync diving",
            "Price": 25.8,
            "Quantity": 1
        },
        {
            "Cost": 3.3,
            "Name": "Water bottle",
            "Price": 9.3,
            "Quantity": 3
        }
    ],
    "Promotions": [
        {
            "Discount": 0.05,
            "Per_Quantity": 2,
            "Product": "Water bottle"
        },
        {
            "Discount": 0.25,
            "Per_Quantity": 1,
            "Product": "Sync diving"
        }
    ],
    "Reference": "5593822:280202:01875",
    "Sequence": 1875,
    "Terminal": 3,
    "Total": 46.32
}