{
    "Business": {
        "ABN": "559 38 22",
        "Name": "Penguin Swim School"
    },
    "Cashier": "Kevin",
    "Date": "2026/05/22",
    "GST": 6.6,
    "Payments": [
        {
            "Amount": 14.52,
            "Method": "Credit Card"
        },
        {
            "Amount": 58.08,
            "Method": "BPAY"
        }
    ],
    "Products": [
        {
            "Cost": 7.8,
            "Name": "Aquaerobics",
            "Price": 14.6,
            "Quantity": 2
        },
        {
            "Cost": 2.8,
            "Name": "Hot chips",
            "Price": 6.2,
            "Quantity": 2
        },
        {
            "Cost": 3.9,
            "Name": "Swim cap",
            "Price": 12.4,
            "Quantity": 2
        },
        {
            "Cost": 3.9,
            "Name": "Swim cap",
            "Price": 12.4,
            "Quantity": 1
        }
    ],
    "Promotions": [
        {
            "Discount": 0.25,
            "Per_Quantity": 2,
            "Product": "Swim cap"
        }
    ],
    "Reference": "5593822:260522:01247",
    "Sequence": 1247,
    "Terminal": 3,
    "Total": 72.6
}