{
    "Business": {
        "ABN": "559 38 22",
        "Name": "Penguin Swim School"
    },
    "Cashier": "Jennifer",
    "Date": "2024/04/13",
    "GST": 18.07,
    "Payments": [
        {
            "Amount": 198.82,
            "Method": "EFTPOS"
        }
    ],
    "Products": [
        {
            "Cost": 10.2,
            "Name": "Towel",
            "Price": 16.6,
            "Quantity": 3
        },
        {
            "Cost": 11.4,
            "Name": "Sync diving",
            "Price": 22.0,
            "Quantity": 1
        },
        {
            "Cost": 22.2,
            "Name": "Rescue training",
            "Price": 55.0,
            "Quantity": 3
        }
    ],
    "Promotions": [
        {
            "Discount": 0.15,
            "Per_Quantity": 2,
            "Product": "Towel"
        },
        {
            "Discount": 0.2,
            "Per_Quantity": 1,
            "Product": "Rescue training"
        }
    ],
    "Reference": "5593822:240413:00545",
    "Sequence": 545,
    "Terminal": 2,
    "Total": 198.82
}