{
    "Business": {
        "ABN": "559 38 22",
        "Name": "Penguin Swim School"
    },
    "Cashier": "Donna",
    "Date": "2026/11/13",
    "GST": 6.3,
    "Payments": [
        {
            "Amount": 69.25,
            "Method": "Cash"
        }
    ],
    "Products": [
        {
            "Cost": 11.2,
            "Name": "Infant lesson",
            "Price": 18.2,
            "Quantity": 2
        },
        {
            "Cost": 7.8,
            "Name": "Waterpolo",
            "Price": 14.6,
            "Quantity": 3
        }
    ],
    "Promotions": [
        {
            "Discount": 0.25,
            "Per_Quantity": 3,
            "Product": "Waterpolo"
        }
    ],
    "Reference": "5593822:261113:01411",
    "Sequence": 1411,
    "Terminal": 3,
    "Total": 69.25
}