{
    "Business": {
        "ABN": "559 38 22",
        "Name": "Penguin Swim School"
    },
    "Cashier": "Jeffrey",
    "Customer": {
        "Name": "Elijah",
        "Points_Earnt": 0
    },
    "Date": "2029/06/29",
    "GST": 1.68,
    "Payments": [
        {
            "Amount": 18.46,
            "Method": "Loyalty Points"
        }
    ],
    "Products": [
        {
            "Cost": 4.0,
            "Name": "Shampoo",
            "Price": 7.1,
            "Quantity": 3
        }
    ],
    "Promotions": [
        {
            "Discount": 0.2,
            "Per_Quantity": 2,
            "Product": "Shampoo"
        }
    ],
    "Reference": "5593822:290629:02398",
    "Sequence": 2398,
    "Terminal": 1,
    "Total": 18.46
}