{
    "Business": {
        "ABN": "962 65 10",
        "Name": "Please Bring Pizza Pronto"
    },
    "Cashier": "Amber",
    "Date": "2028/06/29",
    "GST": 8.82,
    "Payments": [
        {
            "Amount": 97.06,
            "Method": "BPAY"
        }
    ],
    "Products": [
        {
            "Cost": 5.5,
            "Name": "Spicy chicken",
            "Price": 17.2,
            "Quantity": 3
        },
        {
            "Cost": 3.2,
            "Name": "Pancakes",
            "Price": 9.3,
            "Quantity": 1
        },
        {
            "Cost": 5.2,
            "Name": "Garlic bread",
            "Price": 7.9,
            "Quantity": 3
        },
        {
            "Cost": 7.1,
            "Name": "Pepperoni",
            "Price": 17.2,
            "Quantity": 1
        }
    ],
    "Promotions": [
        {
            "Discount": 0.3,
            "Per_Quantity": 2,
            "Product": "Garlic bread"
        }
    ],
    "Reference": "9626510:280629:03457",
    "Sequence": 3457,
    "Terminal": 5,
    "Total": 97.06
}