{
    "Business": {
        "ABN": "962 65 10",
        "Name": "Please Bring Pizza Pronto"
    },
    "Cashier": "Tara",
    "Customer": {
        "Name": "Aaron",
        "Points_Earnt": 3400
    },
    "Date": "2022/08/25",
    "GST": 3.09,
    "Payments": [
        {
            "Amount": 34.0,
            "Method": "BPAY"
        }
    ],
    "Products": [
        {
            "Cost": 9.6,
            "Name": "Three meat",
            "Price": 16.0,
            "Quantity": 1
        },
        {
            "Cost": 3.0,
            "Name": "Chips",
            "Price": 6.0,
            "Quantity": 3
        }
    ],
    "Promotions": [],
    "Reference": "9626510:220825:00072",
    "Sequence": 72,
    "Terminal": 5,
    "Total": 34.0
}