{
    "Business": {
        "ABN": "962 65 10",
        "Name": "Please Bring Pizza Pronto"
    },
    "Cashier": "Tara",
    "Customer": {
        "Name": "Mary",
        "Points_Earnt": 1200
    },
    "Date": "2022/12/09",
    "GST": 1.09,
    "Payments": [
        {
            "Amount": 7.2,
            "Method": "Debit Card"
        },
        {
            "Amount": 4.8,
            "Method": "EFTPOS"
        }
    ],
    "Products": [
        {
            "Cost": 3.0,
            "Name": "Chips",
            "Price": 6.0,
            "Quantity": 1
        },
        {
            "Cost": 3.6,
            "Name": "Garlic bread",
            "Price": 6.0,
            "Quantity": 1
        }
    ],
    "Promotions": [],
    "Reference": "9626510:221209:00199",
    "Sequence": 199,
    "Terminal": 3,
    "Total": 12.0
}