{
    "Business": {
        "ABN": "962 65 10",
        "Name": "Please Bring Pizza Pronto"
    },
    "Cashier": "Ronald",
    "Date": "2026/05/30",
    "GST": 7.9,
    "Payments": [
        {
            "Amount": 52.16,
            "Method": "Gift Card"
        },
        {
            "Amount": 34.77,
            "Method": "BPAY"
        }
    ],
    "Products": [
        {
            "Cost": 1.9,
            "Name": "Soft drink 2L",
            "Price": 5.5,
            "Quantity": 2
        },
        {
            "Cost": 7.6,
            "Name": "Hawaiian",
            "Price": 14.6,
            "Quantity": 2
        },
        {
            "Cost": 1.9,
            "Name": "Soft drink 2L",
            "Price": 5.5,
            "Quantity": 3
        },
        {
            "Cost": 5.0,
            "Name": "Spicy chicken",
            "Price": 15.8,
            "Quantity": 2
        }
    ],
    "Promotions": [
        {
            "Discount": 0.05,
            "Per_Quantity": 1,
            "Product": "Soft drink 2L"
        }
    ],
    "Reference": "9626510:260530:02079",
    "Sequence": 2079,
    "Terminal": 2,
    "Total": 86.93
}