{
    "Business": {
        "ABN": "962 65 10",
        "Name": "Please Bring Pizza Pronto"
    },
    "Cashier": "Amber",
    "Date": "2025/07/23",
    "GST": 4.3,
    "Payments": [
        {
            "Amount": 47.29,
            "Method": "EFTPOS"
        }
    ],
    "Products": [
        {
            "Cost": 3.6,
            "Name": "Chips",
            "Price": 6.9,
            "Quantity": 3
        },
        {
            "Cost": 1.7,
            "Name": "Soft drink 2L",
            "Price": 5.2,
            "Quantity": 1
        },
        {
            "Cost": 8.5,
            "Name": "Ham and Cheese",
            "Price": 13.8,
            "Quantity": 2
        }
    ],
    "Promotions": [
        {
            "Discount": 0.3,
            "Per_Quantity": 3,
            "Product": "Chips"
        }
    ],
    "Reference": "9626510:250723:01565",
    "Sequence": 1565,
    "Terminal": 3,
    "Total": 47.29
}