{
    "Business": {
        "ABN": "962 65 10",
        "Name": "Please Bring Pizza Pronto"
    },
    "Cashier": "Levi",
    "Date": "2029/03/16",
    "GST": 1.78,
    "Payments": [
        {
            "Amount": 19.6,
            "Method": "Cash"
        }
    ],
    "Products": [
        {
            "Cost": 3.4,
            "Name": "Pancakes",
            "Price": 9.8,
            "Quantity": 2
        }
    ],
    "Promotions": [],
    "Reference": "9626510:290316:03982",
    "Sequence": 3982,
    "Terminal": 1,
    "Total": 19.6
}