{
    "Business": {
        "ABN": "962 65 10",
        "Name": "Please Bring Pizza Pronto"
    },
    "Cashier": "Amber",
    "Date": "2027/12/11",
    "GST": 3.63,
    "Payments": [
        {
            "Amount": 31.92,
            "Method": "Gift Card"
        },
        {
            "Amount": 7.98,
            "Method": "BPAY"
        }
    ],
    "Products": [
        {
            "Cost": 4.9,
            "Name": "Vego",
            "Price": 15.2,
            "Quantity": 1
        },
        {
            "Cost": 4.9,
            "Name": "Garlic bread",
            "Price": 7.6,
            "Quantity": 3
        },
        {
            "Cost": 4.9,
            "Name": "Garlic bread",
            "Price": 7.6,
            "Quantity": 1
        }
    ],
    "Promotions": [
        {
            "Discount": 0.25,
            "Per_Quantity": 3,
            "Product": "Garlic bread"
        }
    ],
    "Reference": "9626510:271211:03074",
    "Sequence": 3074,
    "Terminal": 4,
    "Total": 39.9
}