{
    "Business": {
        "ABN": "962 65 10",
        "Name": "Please Bring Pizza Pronto"
    },
    "Cashier": "Tara",
    "Customer": {
        "Name": "Jeremy",
        "Points_Earnt": 3188
    },
    "Date": "2024/07/21",
    "GST": 2.9,
    "Payments": [
        {
            "Amount": 31.89,
            "Method": "Credit Card"
        }
    ],
    "Products": [
        {
            "Cost": 1.6,
            "Name": "Soft drink 2L",
            "Price": 5.0,
            "Quantity": 3
        },
        {
            "Cost": 2.1,
            "Name": "Cheese bread",
            "Price": 6.6,
            "Quantity": 3
        }
    ],
    "Promotions": [
        {
            "Discount": 0.15,
            "Per_Quantity": 3,
            "Product": "Soft drink 2L"
        },
        {
            "Discount": 0.05,
            "Per_Quantity": 2,
            "Product": "Cheese bread"
        }
    ],
    "Reference": "9626510:240721:01005",
    "Sequence": 1005,
    "Terminal": 1,
    "Total": 31.89
}