{
    "Business": {
        "ABN": "962 65 10",
        "Name": "Please Bring Pizza Pronto"
    },
    "Cashier": "Levi",
    "Date": "2028/09/28",
    "GST": 0.85,
    "Payments": [
        {
            "Amount": 9.3,
            "Method": "Debit Card"
        }
    ],
    "Products": [
        {
            "Cost": 3.2,
            "Name": "Pancakes",
            "Price": 9.3,
            "Quantity": 1
        }
    ],
    "Promotions": [],
    "Reference": "9626510:280928:03632",
    "Sequence": 3632,
    "Terminal": 2,
    "Total": 9.3
}