{
    "Business": {
        "ABN": "962 65 10",
        "Name": "Please Bring Pizza Pronto"
    },
    "Cashier": "Levi",
    "Date": "2028/09/17",
    "GST": 9.11,
    "Payments": [
        {
            "Amount": 50.11,
            "Method": "Credit Card"
        },
        {
            "Amount": 50.11,
            "Method": "Debit Card"
        }
    ],
    "Products": [
        {
            "Cost": 5.2,
            "Name": "Garlic bread",
            "Price": 7.9,
            "Quantity": 3
        },
        {
            "Cost": 5.2,
            "Name": "Garlic bread",
            "Price": 7.9,
            "Quantity": 2
        },
        {
            "Cost": 3.2,
            "Name": "Pancakes",
            "Price": 9.3,
            "Quantity": 2
        },
        {
            "Cost": 7.1,
            "Name": "Pepperoni",
            "Price": 17.2,
            "Quantity": 3
        }
    ],
    "Promotions": [
        {
            "Discount": 0.3,
            "Per_Quantity": 2,
            "Product": "Garlic bread"
        }
    ],
    "Reference": "9626510:280917:03612",
    "Sequence": 3612,
    "Terminal": 3,
    "Total": 100.22
}