{
    "Business": {
        "ABN": "962 65 10",
        "Name": "Please Bring Pizza Pronto"
    },
    "Cashier": "Ronald",
    "Customer": {
        "Name": "Mary",
        "Points_Earnt": 9490
    },
    "Date": "2026/12/03",
    "GST": 8.63,
    "Payments": [
        {
            "Amount": 56.65,
            "Method": "Cash"
        },
        {
            "Amount": 38.25,
            "Method": "Debit Card"
        }
    ],
    "Products": [
        {
            "Cost": 3.9,
            "Name": "Chips",
            "Price": 7.3,
            "Quantity": 1
        },
        {
            "Cost": 4.7,
            "Name": "Vego",
            "Price": 14.6,
            "Quantity": 2
        },
        {
            "Cost": 4.7,
            "Name": "Garlic bread",
            "Price": 7.3,
            "Quantity": 2
        },
        {
            "Cost": 7.6,
            "Name": "Hawaiian",
            "Price": 14.6,
            "Quantity": 3
        }
    ],
    "Promotions": [],
    "Reference": "9626510:261203:02389",
    "Sequence": 2389,
    "Terminal": 5,
    "Total": 94.9
}