{
    "Business": {
        "ABN": "962 65 10",
        "Name": "Please Bring Pizza Pronto"
    },
    "Cashier": "Christian",
    "Customer": {
        "Name": "Robert",
        "Points_Earnt": 2200
    },
    "Date": "2022/07/21",
    "GST": 2.0,
    "Payments": [
        {
            "Amount": 22.0,
            "Method": "EFTPOS"
        }
    ],
    "Products": [
        {
            "Cost": 9.6,
            "Name": "Three meat",
            "Price": 16.0,
            "Quantity": 1
        },
        {
            "Cost": 3.0,
            "Name": "Chips",
            "Price": 6.0,
            "Quantity": 1
        }
    ],
    "Promotions": [],
    "Reference": "9626510:220721:00024",
    "Sequence": 24,
    "Terminal": 2,
    "Total": 22.0
}