{
    "Business": {
        "ABN": "962 65 10",
        "Name": "Please Bring Pizza Pronto"
    },
    "Cashier": "Ronald",
    "Date": "2023/11/22",
    "GST": 11.21,
    "Payments": [
        {
            "Amount": 68.95,
            "Method": "Cash"
        },
        {
            "Amount": 54.37,
            "Method": "Credit Card"
        }
    ],
    "Products": [
        {
            "Cost": 10.2,
            "Name": "Three meat",
            "Price": 16.8,
            "Quantity": 3
        },
        {
            "Cost": 3.2,
            "Name": "Chips",
            "Price": 6.3,
            "Quantity": 3
        },
        {
            "Cost": 10.2,
            "Name": "Three meat",
            "Price": 16.8,
            "Quantity": 3
        },
        {
            "Cost": 1.5,
            "Name": "Soft drink 2L",
            "Price": 4.8,
            "Quantity": 2
        }
    ],
    "Promotions": [
        {
            "Discount": 0.05,
            "Per_Quantity": 3,
            "Product": "Chips"
        },
        {
            "Discount": 0.05,
            "Per_Quantity": 1,
            "Product": "Three meat"
        }
    ],
    "Reference": "9626510:231122:00658",
    "Sequence": 658,
    "Terminal": 4,
    "Total": 123.32
}